odoo/addons/res_partner_operating_unit/README.rst
odoo/addons/res_partner_operating_unit/__init__.py
odoo/addons/res_partner_operating_unit/__manifest__.py
odoo/addons/res_partner_operating_unit/i18n/it.po
odoo/addons/res_partner_operating_unit/i18n/pt.po
odoo/addons/res_partner_operating_unit/i18n/res_partner_operating_unit.pot
odoo/addons/res_partner_operating_unit/models/__init__.py
odoo/addons/res_partner_operating_unit/models/res_partner.py
odoo/addons/res_partner_operating_unit/models/res_users.py
odoo/addons/res_partner_operating_unit/readme/CONTRIBUTORS.md
odoo/addons/res_partner_operating_unit/readme/CREDITS.md
odoo/addons/res_partner_operating_unit/readme/DESCRIPTION.md
odoo/addons/res_partner_operating_unit/readme/USAGE.md
odoo/addons/res_partner_operating_unit/static/description/icon.png
odoo/addons/res_partner_operating_unit/static/description/index.html
odoo/addons/res_partner_operating_unit/tests/__init__.py
odoo/addons/res_partner_operating_unit/tests/test_res_partner_operating_unit.py
odoo/addons/res_partner_operating_unit/views/res_partner_view.xml
odoo_addon_res_partner_operating_unit-18.0.1.1.1.2.dist-info/METADATA
odoo_addon_res_partner_operating_unit-18.0.1.1.1.2.dist-info/WHEEL
odoo_addon_res_partner_operating_unit-18.0.1.1.1.2.dist-info/top_level.txt
odoo_addon_res_partner_operating_unit-18.0.1.1.1.2.dist-info/RECORD
